pgconnect/Column.py
pgconnect/Connection.py
pgconnect/DataType.py
pgconnect/Filters.py
pgconnect/Table.py
pgconnect/__init__.py
pgconnect/examples.py
pgconnect-0.7.0.dist-info/licenses/LICENSE
pgconnect-0.7.0.dist-info/METADATA
pgconnect-0.7.0.dist-info/WHEEL
pgconnect-0.7.0.dist-info/top_level.txt
pgconnect-0.7.0.dist-info/RECORD
