Metadata-Version: 2.4
Name: pgconnect
Version: 0.7.0
Summary: A PostgreSQL connection and ORM library
Home-page: https://github.com/AdnanBinPulok/PgConnect
Author: AdnanBinPulok
Author-email: Adnan Bin Pulok <adnanbinpulok@gmail.com>
Project-URL: Homepage, https://github.com/adnanbinpulok
Project-URL: GitHub, https://github.com/adnanbinpulok/pgconnect
Project-URL: Issues, https://github.com/adnanbinpulok/pgconnect/issues
Classifier: Programming Language :: Python :: 3
Classifier: License :: OSI Approved :: MIT License
Classifier: Operating System :: OS Independent
Requires-Python: >=3.6
License-File: LICENSE
Requires-Dist: asyncpg
Requires-Dist: cachetools
Requires-Dist: redis
Dynamic: author
Dynamic: home-page
Dynamic: license-file
Dynamic: requires-python
